strigiform/__init__.py
strigiform/alerts/__init__.py
strigiform/app/__init__.py
strigiform/app/queries.py
strigiform/app/streamlit.py
strigiform/core/__init__.py
strigiform/core/cli.py
strigiform/core/commands/__init__.py
strigiform/core/commands/_helpers.py
strigiform/core/commands/hotspots.py
strigiform/core/commands/launch.py
strigiform/core/commands/test.py
strigiform/core/commands/vault.py
strigiform/data/analyze/__init__.py
strigiform/data/analyze/desc_stats.py
strigiform/data/fetch/__init__.py
strigiform/data/fetch/birdcast.py
strigiform/data/fetch/ebird.py
strigiform/data/fetch/twitter.py
strigiform/data/import/ebird.py
strigiform/data/load/ebird_observations.py
strigiform/data/load/ebird_taxonomy.py
strigiform/data/storage/README.md
strigiform/data/storage/__init__.py
strigiform/data/storage/create_tables.py
strigiform/data/storage/maria/setup
strigiform/data/storage/populate_taxonomy_table.py
strigiform/data/storage/postgres/__init__.py
strigiform/data/storage/postgres/postgres.py
strigiform/data/storage/postgres/setup
strigiform/data/storage/redis/setup
strigiform/py.typed
strigiform/secrets/__init__.py
strigiform/secrets/vault.py
strigiform/secrets/vault_config.hcl
strigiform/util/api.py
strigiform/util/config.py
strigiform/util/logger.py
strigiform-0.0.4.dist-info/entry_points.txt
strigiform-0.0.4.dist-info/LICENSE.rst
strigiform-0.0.4.dist-info/WHEEL
strigiform-0.0.4.dist-info/METADATA
strigiform-0.0.4.dist-info/RECORD
