Metadata-Version: 2.1
Name: strigiform
Version: 0.0.4
Summary: strigiform
Home-page: https://github.com/X-McKay/strigiform
License: MIT
Author: Alex McKay
Author-email: aldmckay@gmail.com
Requires-Python: >=3.7.9,<4.0.0
Classifier: License :: OSI Approved :: MIT License
Classifier: Programming Language :: Python :: 3
Classifier: Programming Language :: Python :: 3.10
Classifier: Programming Language :: Python :: 3.7
Classifier: Programming Language :: Python :: 3.8
Classifier: Programming Language :: Python :: 3.9
Requires-Dist: SQLAlchemy (==1.4.23)
Requires-Dist: botocore (>=1.21.29,<2.0.0)
Requires-Dist: click
Requires-Dist: click-help-colors (>=0.9.1,<0.10.0)
Requires-Dist: configparser (>=5.0.2,<6.0.0)
Requires-Dist: hvac (>=0.11.2,<0.12.0)
Requires-Dist: importlib-metadata (<4.9.0)
Requires-Dist: mock (>=4.0.3,<5.0.0)
Requires-Dist: nox-poetry (>=0.8.6,<0.9.0)
Requires-Dist: pandas (>=1.2.5,<2.0.0)
Requires-Dist: pandas-stubs (>=1.2.0,<2.0.0)
Requires-Dist: parameterized (>=0.8.1,<0.9.0)
Requires-Dist: psycopg2 (>=2.9.1,<3.0.0)
Requires-Dist: pytest-responsemock[dev] (>=1.0.1,<2.0.0)
Requires-Dist: requests (==2.26.0)
Requires-Dist: requests-mock
Requires-Dist: sql (>=0.4.0,<0.5.0)
Requires-Dist: streamlit (>=1.0.0,<2.0.0)
Requires-Dist: types-requests (>=2.25.0,<3.0.0)
Project-URL: Changelog, https://github.com/X-McKay/strigiform/releases
Project-URL: Documentation, https://strigiform.readthedocs.io
Project-URL: Repository, https://github.com/X-McKay/strigiform
